wrf_ensembly/__init__.py
wrf_ensembly/cdo.py
wrf_ensembly/cli.py
wrf_ensembly/click_utils.py
wrf_ensembly/config.py
wrf_ensembly/console.py
wrf_ensembly/cycling.py
wrf_ensembly/external.py
wrf_ensembly/fortran_namelists.py
wrf_ensembly/jobfiles.py
wrf_ensembly/nco.py
wrf_ensembly/obs_sequence.py
wrf_ensembly/perturbations.py
wrf_ensembly/processors.py
wrf_ensembly/statistics.py
wrf_ensembly/templates.py
wrf_ensembly/test_utils.py
wrf_ensembly/update_bc.py
wrf_ensembly/utils.py
wrf_ensembly/wrf.py
wrf_ensembly/commands/ensemble.py
wrf_ensembly/commands/experiment.py
wrf_ensembly/commands/obs_sequence.py
wrf_ensembly/commands/observations.py
wrf_ensembly/commands/postprocess.py
wrf_ensembly/commands/preprocess.py
wrf_ensembly/commands/slurm.py
wrf_ensembly/commands/status.py
wrf_ensembly/commands/validation.py
wrf_ensembly/config_templates/aris_chem_4.5.2.toml
wrf_ensembly/config_templates/iridium_chem_4.6.0.toml
wrf_ensembly/experiment/__init__.py
wrf_ensembly/experiment/database.py
wrf_ensembly/experiment/dataclasses.py
wrf_ensembly/experiment/experiment.py
wrf_ensembly/experiment/observations.py
wrf_ensembly/experiment/paths.py
wrf_ensembly/observations/__init__.py
wrf_ensembly/observations/cli.py
wrf_ensembly/observations/dart.py
wrf_ensembly/observations/io.py
wrf_ensembly/observations/mapping.py
wrf_ensembly/observations/operations.py
wrf_ensembly/observations/plotting.py
wrf_ensembly/observations/superorbing.py
wrf_ensembly/observations/utils.py
wrf_ensembly/observations/converters/__init__.py
wrf_ensembly/observations/converters/aeronet.py
wrf_ensembly/observations/converters/remotap_spexone.py
wrf_ensembly/template_files/dart_input.nml.j2
wrf_ensembly/template_files/namelist.wps.j2
wrf_ensembly/template_files/slurm_job.sh.j2
wrf_ensembly/template_files/wrf_namelist.input.j2
wrf_ensembly-1.0.0.dist-info/METADATA
wrf_ensembly-1.0.0.dist-info/WHEEL
wrf_ensembly-1.0.0.dist-info/entry_points.txt
wrf_ensembly-1.0.0.dist-info/RECORD
